turbostl/__init__.py
turbostl/__main__.py
turbostl/cut/__init__.py
turbostl/cut/__main__.py
turbostl-0.31.1.dist-info/licenses/LICENSE
turbostl-0.31.1.dist-info/METADATA
turbostl-0.31.1.dist-info/WHEEL
turbostl-0.31.1.dist-info/top_level.txt
turbostl-0.31.1.dist-info/RECORD
